{"Bedroom": {"Size": [-260, -140, 520, 280], "Furnitures": {"Bed": {"Size": [[-105, -40, 210, 180]]}, "Wardrobe": {"Size": [[200, 20, 60, 120]]}}}, "Livingroom": {"Size": [-260, -580, 520, 440], "Furnitures": {"Sofa": {"Size": [[-40, -520, 80, 140]]}, "TV": {"Size": [[-260, -500, 60, 100]]}, "Dinner_Table": {"Size": [[-260, -285, 120, 80]]}, "Chair": {"Size": [[-130, -265, 40, 40], [-220, -195, 40, 40]]}}, "Toilet": {"Size": [140, -400, 120, 90]}, "Bathroom": {"Size": [140, -580, 120, 180]}}, "Doors": {"Entrance": {"Size": [-230, -580, 60, 0]}, "Toilet_Door": {"Size": [140, -385, 0, 60]}, "Bathroom_Door": {"Size": [140, -520, 0, 60]}}, "Walls": [[[-260, -580], [-260, 140]], [[260, -310], [260, 140]], [[-260, 140], [260, 140]], [[-260, -580], [260, -580]]], "Boundary": [[-260, 260], [-580, 140]]}