{"Bedroom": {"Size": [-180, -130, 360, 260], "Furnitures": {"Bed": {"Size": [[-180, -130, 210, 120]]}, "Wardrobe": {"Size": [[120, 40, 60, 60]]}}}, "Kitchen": {"Size": [-180, 410, 360, 200], "Furnitures": {"Kitchen_Stove": {"Size": [[-180, 440, 120, 60]]}, "Cupboard": {"Size": [[-180, 560, 100, 50]]}, "Refrigerator": {"Size": [[120, 490, 60, 60]]}, "Trash_Bin": {"Size": [[-20, 580, 60, 30]]}}}, "Livingroom": {"Size": [-180, 130, 480, 280], "Furnitures": {"Dinner_Table": {"Size": [[-170, 190, 80, 80]]}, "Chair": {"Size": [[-80, 210, 40, 40]]}}, "Toilet": {"Size": [180, 320, 120, 90]}, "Bathroom": {"Size": [180, 140, 120, 180]}}, "Doors": {"Entrance": {"Size": [90, 610, 60, 0]}, "Toilet_Door": {"Size": [180, 335, 0, 60]}, "Bathroom_Door": {"Size": [180, 200, 0, 60]}}, "Walls": [[[-180, -130], [-180, 610]], [[180, -130], [180, 130]], [[180, 410], [180, 610]], [[300, 130], [300, 140]], [[-180, -130], [180, -130]], [[180, 130], [300, 130]], [[-180, 610], [180, 610]]], "Boundary": [[-180, 300], [-130, 610]]}