{"Bedroom": {"Size": [-150, -250, 300, 500], "Furnitures": {"Bed": {"Size": [[-150, -165, 210, 180]]}, "Wardrobe": {"Size": [[-150, 123, 60, 80]]}}, "Bathroom": {"Size": [-30, 130, 180, 120]}}, "Kitchen": {"Size": [150, -250, 260, 380], "Furnitures": {"Kitchen_Stove": {"Size": [[290, 10, 120, 60]]}, "Cupboard": {"Size": [[290, -220, 120, 50]]}, "Trash_Bin": {"Size": [[350, -95, 60, 30]]}}, "Toilet": {"Size": [150, 130, 90, 120]}}, "Livingroom": {"Size": [-150, -590, 660, 340], "Furnitures": {"Sofa": {"Size": [[30, -590, 80, 190]]}, "TV": {"Size": [[290, -555, 40, 120]]}, "Dinner_Table": {"Size": [[410, -440, 80, 160]]}, "Chair": {"Size": [[360, -380, 40, 40], [430, -490, 40, 40]]}}}, "Doors": {"Entrance": {"Size": [270, 130, 60, 0]}, "Toilet_Door": {"Size": [165, 130, 60, 0]}, "Bathroom_Door": {"Size": [30, 130, 60, 0]}}, "Walls": [[[-150, 250], [-30, 250]], [[240, 130], [410, 130]], [[410, -250], [510, -250]], [[-150, -590], [510, -590]], [[-150, -590], [-150, 250]], [[410, -250], [410, 130]], [[510, -590], [510, -250]]], "Boundary": [[-150, 510], [-590, 250]]}