{"Bedroom": {"Size": [-220, -180, 440, 360], "Furnitures": {"Bed": {"Size": [[-220, -30, 210, 180]]}, "Wardrobe": {"Size": [[-220, -180, 120, 60]]}}, "Bathroom": {"Size": [220, 0, 120, 180]}}, "Kitchen": {"Size": [-100, 180, 320, 340], "Furnitures": {"Kitchen_Stove": {"Size": [[-100, 460, 180, 60]]}, "Cupboard": {"Size": [[155, 370, 50, 150]]}, "Refrigerator": {"Size": [[-100, 340, 60, 60]]}, "Wash_Machine": {"Size": [[-100, 220, 60, 60]]}}, "Toilet": {"Size": [220, 180, 120, 90]}}, "Doors": {"Entrance": {"Size": [220, -150, 0, 60]}, "Toilet_Door": {"Size": [220, 195, 0, 60]}, "Bathroom_Door": {"Size": [220, 60, 0, 60]}}, "Walls": [[[-220, -180], [-220, 180]], [[-100, 180], [-100, 520]], [[220, -180], [220, 0]], [[220, 270], [220, 520]], [[-220, -180], [220, -180]], [[-220, 180], [-100, 180]], [[-100, 520], [220, 520]]], "Boundary": [[-220, 340], [-180, 520]]}