{"Bedroom": {"Size": [-230, -140, 460, 280], "Furnitures": {"Bed": {"Size": [[20, -70, 90, 210]]}}, "Bathroom": {"Size": [-230, -140, 120, 180]}}, "Kitchen": {"Size": [-110, -420, 340, 280], "Furnitures": {"Kitchen_Stove": {"Size": [[45, -420, 60, 180]]}, "Cupboard": {"Size": [[-88, -420, 50, 120]]}, "Trash_Bin": {"Size": [[170, -420, 30, 60]]}}, "Toilet": {"Size": [-230, -230, 120, 90]}}, "Livingroom": {"Size": [230, -420, 460, 480], "Furnitures": {"Dinner_Table": {"Size": [[460, -110, 160, 80]]}, "Chair": {"Size": [[520, -20, 40, 40], [410, -90, 40, 40], [520, -160, 40, 40], [630, -90, 40, 40]]}, "Sofa": {"Size": [[390, -420, 80, 190]]}, "TV": {"Size": [[630, -385, 60, 120]]}}}, "Doors": {"Entrance": {"Size": [140, 140, 60, 0]}, "Toilet_Door": {"Size": [-110, -215, 0, 60]}, "Bathroom_Door": {"Size": [-110, -80, 0, 60]}}, "Walls": [[[-230, 40], [-230, 140]], [[-110, -420], [-110, -230]], [[230, 60], [230, 140]], [[690, -420], [690, 60]], [[-230, 140], [230, 140]], [[230, 60], [690, 60]], [[-110, -420], [690, -420]]], "Boundary": [[-230, 690], [-420, 140]]}