{"Bedroom": {"Size": [-260, -140, 520, 280], "Furnitures": {"Bed": {"Size": [[50, -80, 210, 180]]}, "Nightstand": {"Size": [[220, 100, 40, 40]]}, "Wardrobe": {"Size": [[-230, 40, 60, 100]]}}}, "Kitchen": {"Size": [-260, -420, 400, 280], "Furnitures": {"Kitchen_Stove": {"Size": [[-40, -420, 180, 60]]}, "Cupboard": {"Size": [[-10, -220, 150, 50]]}}, "Toilet": {"Size": [-260, -540, 90, 120]}}, "Livingroom": {"Size": [-640, -420, 380, 540], "Furnitures": {"Dinner_Table": {"Size": [[-560, -160, 120, 80]]}, "Chair": {"Size": [[-520, -70, 40, 40], [-430, -140, 40, 40], [-520, -210, 40, 40]]}}, "Bathroom": {"Size": [-440, -540, 180, 120]}}, "Doors": {"Entrance": {"Size": [170, -140, 60, 0]}, "Toilet_Door": {"Size": [-245, -420, 60, 0]}, "Bathroom_Door": {"Size": [-380, -420, 60, 0]}}, "Walls": [[[260, -140], [260, 140]], [[140, -420], [140, -140]], [[-260, 120], [-260, 140]], [[-640, -420], [-640, 120]], [[-260, 140], [260, 140]], [[-640, 120], [-260, 120]], [[140, -140], [260, -140]], [[-170, -420], [140, -420]], [[-640, -420], [-440, -420]]], "Boundary": [[-640, 260], [-540, 140]]}