{"Bedroom": {"Size": [-150, -150, 300, 300], "Furnitures": {"Bed": {"Size": [[-60, -60, 210, 90]]}}}, "Kitchen": {"Size": [-370, -150, 220, 300], "Furnitures": {"Kitchen_Stove": {"Size": [[-370, -150, 60, 120]]}, "Cupboard": {"Size": [[-370, 30, 100, 50]]}, "Trash_Bin": {"Size": [[-245, -150, 30, 60]]}}}, "Livingroom": {"Size": [-230, 150, 380, 340], "Furnitures": {"Dinner_Table": {"Size": [[60, 200, 80, 100]]}, "Chair": {"Size": [[10, 230, 40, 40]]}, "Sofa": {"Size": [[70, 360, 80, 90]]}, "TV": {"Size": [[-150, 365, 40, 80]]}}, "Toilet": {"Size": [-350, 220, 120, 90]}, "Bathroom": {"Size": [-350, 310, 120, 180]}}, "Doors": {"Entrance": {"Size": [-180, -150, 60, 0]}, "Toilet_Door": {"Size": [-230, 235, 0, 60]}, "Bathroom_Door": {"Size": [-230, 370, 0, 60]}}, "Walls": [[[-370, -150], [150, -150]], [[-370, 150], [-230, 150]], [[-230, 490], [150, 490]], [[150, -150], [150, 490]], [[-370, -150], [-370, 150]], [[-230, 150], [-230, 220]]], "Boundary": [[-370, 150], [-150, 490]]}